core
mint
