Metadata-Version: 2.1
Name: mint-api
Version: 1.0.0.post3
Summary: A execution manager cli for execution
Home-page: https://github.com/mintproject/mint-execution-manager
Author: Maximiliano Osorio
Author-email: mosorio@isi.edu
License: Apache-2
Platform: UNKNOWN
Classifier: License :: OSI Approved :: Apache Software License
Classifier: Development Status :: 3 - Alpha
Classifier: Programming Language :: Python
Classifier: Programming Language :: Python :: 3
Classifier: Programming Language :: Python :: 3.5
Classifier: Programming Language :: Python :: 3.6
Classifier: Programming Language :: Python :: 3.7
Classifier: Intended Audience :: Science/Research
Classifier: Operating System :: Unix
Requires-Python: >=3.5.0
